[
  {
    "name": "Nordic Moose ",
    "ingredients": [
      "Moose meat",
      "Chanterelles",
      "Rosemary dressing"
    ],
    "prize": 9.95
  },
  {
    "name": "Burger of the House",
    "ingredients": [
      "Beef",
      "Tomato",
      "Pickles",
      "Chili maynonaise"
    ],
    "prize": 7.25
  },
  {
    "name": "Three cheeses",
    "ingredients": [
      "Beef",
      "Extra mature cheddar",
      "Mozzarella",
      "Swedish \"Västerbotten\" ",
      "Olives"
    ],
    "prize": 5.5
  },
  {
    "name": "The Cheapskate",
    "ingredients": [
      "Beef",
      "Ketchup",
      "Mustard"
    ],
    "prize": 2.5
  },
  {
    "name": "Surprize",
    "ingredients": [
      "surp1",
      "surp2",
      "surp3"
    ],
    "prize": 6.5
  }
]
